{
    "global": { "show_in_menu_bar": false },
    "profiles": [
        {
            "complex_modifications": {
                "parameters": { "basic.to_if_alone_timeout_milliseconds": 500 },
                "rules": [
                    {
                        "description": "Change right cmd to be cmd+ctrl",
                        "manipulators": [
                            {
                                "from": {
                                    "key_code": "right_command",
                                    "modifiers": { "optional": ["any"] }
                                },
                                "to": [
                                    {
                                        "key_code": "left_control",
                                        "modifiers": ["left_command"]
                                    }
                                ],
                                "type": "basic"
                            }
                        ]
                    },
                    {
                        "description": "Post Esc if Caps is tapped, Control if held.",
                        "manipulators": [
                            {
                                "from": {
                                    "key_code": "left_control",
                                    "modifiers": { "optional": ["any"] }
                                },
                                "to": [
                                    {
                                        "key_code": "left_control",
                                        "lazy": true
                                    }
                                ],
                                "to_if_alone": [{ "key_code": "escape" }],
                                "type": "basic"
                            }
                        ]
                    }
                ]
            },
            "devices": [
                {
                    "identifiers": {
                        "is_keyboard": true,
                        "is_pointing_device": true,
                        "product_id": 45913,
                        "vendor_id": 1133
                    },
                    "ignore": false,
                    "manipulate_caps_lock_led": false
                }
            ],
            "name": "Default profile",
            "selected": true,
            "simple_modifications": [
                {
                    "from": { "key_code": "caps_lock" },
                    "to": [{ "key_code": "left_control" }]
                },
                {
                    "from": { "key_code": "escape" },
                    "to": [{ "key_code": "caps_lock" }]
                }
            ],
            "virtual_hid_keyboard": { "keyboard_type_v2": "ansi" }
        }
    ]
}